samarium62/__init__.py
samarium62/discord/__init__.py
samarium62/discord/component.py
samarium62/discord/embed.py
samarium62/discord/image_processing.py
samarium62/ext/__init__.py
samarium62/ext/checks.py
samarium62-0.0.5.dist-info/LICENSE
samarium62-0.0.5.dist-info/METADATA
samarium62-0.0.5.dist-info/WHEEL
samarium62-0.0.5.dist-info/top_level.txt
samarium62-0.0.5.dist-info/RECORD
