Metadata-Version: 2.1
Name: samarium62
Version: 0.0.5
Summary: A wrapper package for creating custom discord embed
Author-email: GitYACC <shastrysamarth@gmail.com>
Project-URL: Homepage, https://home.page
Project-URL: Bug Tracker, https://github.com/Future-Lib/issues
Classifier: Programming Language :: Python :: 3
Classifier: License :: OSI Approved :: MIT License
Requires-Python: >=3.7
License-File: LICENSE
Requires-Dist: pillow >=9.3.0
